fabfile/__init__.py
fabfile/development.py
fabfile/environment.py
setup_vm/__init__.py
setup_vm/bin/__init__.py
setup_vm/bin/setup_vm.py
setup_vm/tests/__init__.py
setup_vm/tests/test_code_conformance.py
setup_vm/tests/test_setup_vm.py
setup_vm/tests/test_test.py
u1_test_utils-0.5.dist-info/DESCRIPTION.rst
u1_test_utils-0.5.dist-info/METADATA
u1_test_utils-0.5.dist-info/RECORD
u1_test_utils-0.5.dist-info/WHEEL
u1_test_utils-0.5.dist-info/metadata.json
u1_test_utils-0.5.dist-info/top_level.txt
u1testutils/__init__.py
u1testutils/django.py
u1testutils/logging.py
u1testutils/mail.py
u1testutils/wsgi_intercept.py
u1testutils/pay/__init__.py
u1testutils/pay/api.py
u1testutils/pay/data.py
u1testutils/pay/environment.py
u1testutils/pay/selftests/__init__.py
u1testutils/pay/selftests/unit/__init__.py
u1testutils/pay/selftests/unit/test_pay_api_client.py
u1testutils/selftests/__init__.py
u1testutils/selftests/django_project/__init__.py
u1testutils/selftests/django_project/settings.py
u1testutils/selftests/static/__init__.py
u1testutils/selftests/static/test_static_code_analysis.py
u1testutils/selftests/unit/__init__.py
u1testutils/selftests/unit/test_django.py
u1testutils/selftests/unit/test_logging.py
u1testutils/selftests/unit/test_mail.py
u1testutils/sso/__init__.py
u1testutils/sso/api.py
u1testutils/sso/data.py
u1testutils/sso/environment.py
u1testutils/sso/mail.py
u1testutils/sso/selftests/__init__.py
u1testutils/sso/selftests/acceptance/__init__.py
u1testutils/sso/selftests/acceptance/test_sst_helpers.py
u1testutils/sso/selftests/unit/__init__.py
u1testutils/sso/selftests/unit/test_data.py
u1testutils/sso/selftests/unit/test_environment.py
u1testutils/sso/selftests/unit/test_sso_api_client.py
u1testutils/sso/selftests/unit/test_sso_mail.py
u1testutils/sso/sst/__init__.py
u1testutils/sso/sst/pages.py
u1testutils/sst/__init__.py
u1testutils/sst/config.py
u1testutils/sst/selftests/__init__.py
u1testutils/sst/selftests/acceptance/__init__.py
u1testutils/sst/selftests/acceptance/test_page.py
u1testutils/sst/selftests/acceptance/test_string_page.py
u1testutils/sst/selftests/unit/__init__.py
u1testutils/sst/selftests/unit/test_pages.py
