Metadata-Version: 2.0
Name: u1-test-utils
Version: 0.5
Summary: Common testcases and utilities for testing Ubuntu One applications.
Home-page: UNKNOWN
Author: Ricardo Kirkner
Author-email: ricardo.kirkner@canonical.com
License: UNKNOWN
Platform: UNKNOWN
